odoo_plugin_manager-0.6.1.dist-info/licenses/LICENSE
opm/__init__.py
opm/cli/__main__.py
opm/cli/commands/dev.py
opm/cli/commands/diagnose.py
opm/cli/commands/init.py
opm/cli/commands/test.py
opm/cli/commands/update.py
opm/core/docker.py
opm/core/env.py
opm/core/env_cmds.py
opm/core/odoo_rpc.py
opm/core/state.py
opm/core/utils.py
odoo_plugin_manager-0.6.1.dist-info/METADATA
odoo_plugin_manager-0.6.1.dist-info/WHEEL
odoo_plugin_manager-0.6.1.dist-info/entry_points.txt
odoo_plugin_manager-0.6.1.dist-info/top_level.txt
odoo_plugin_manager-0.6.1.dist-info/RECORD
