Metadata-Version: 2.4
Name: odoo-plugin-manager
Version: 0.6.1
Summary: OPM - Plugin Manager for Odoo (CLI)
Author: Ahmet Atakan
License-Expression: GPL-3.0-or-later
Project-URL: Homepage, https://github.com/ahmetatakan/odoo-plugin-manager
Project-URL: Repository, https://github.com/ahmetatakan/odoo-plugin-manager
Project-URL: Issues, https://github.com/ahmetatakan/odoo-plugin-manager/issues
Project-URL: Documentation, https://pypi.org/project/odoo-plugin-manager/
Classifier: Programming Language :: Python :: 3
Classifier: Programming Language :: Python :: 3.10
Classifier: Programming Language :: Python :: 3.11
Classifier: Programming Language :: Python :: 3.12
Classifier: Operating System :: OS Independent
Requires-Python: >=3.10
License-File: LICENSE
Requires-Dist: typer>=0.12.3
Requires-Dist: rich>=13.7.1
Requires-Dist: pyyaml>=6.0.1
Requires-Dist: watchdog>=4.0.2
Requires-Dist: requests>=2.32.0
Requires-Dist: python-dotenv>=1.0.1
Requires-Dist: websockets>=12.0
Provides-Extra: dev
Requires-Dist: build; extra == "dev"
Requires-Dist: twine; extra == "dev"
Requires-Dist: pytest; extra == "dev"
Requires-Dist: black; extra == "dev"
Requires-Dist: ruff; extra == "dev"
Requires-Dist: mypy; extra == "dev"
Dynamic: license-file
